LICENSE.txt
README.md
setup.py
hyperion_link/__init__.py
hyperion_link/hyperion_ng.py
hyperion_link/websocket_wrapper.py
hyperion_link.egg-info/PKG-INFO
hyperion_link.egg-info/SOURCES.txt
hyperion_link.egg-info/dependency_links.txt
hyperion_link.egg-info/requires.txt
hyperion_link.egg-info/top_level.txt