Metadata-Version: 2.1
Name: hyperion-link
Version: 0.0.21
Summary: a connector between hyperion ng json api and python
Home-page: https://github.com/michelgerding/hyperion-link
Author: Michel Gerding
Author-email: michelgerding@gmail.com
License: UNKNOWN
Platform: UNKNOWN
License-File: LICENSE.txt
